Workbook

Sheet Datos Diarios
A1: 45839
A2: CLIENTE | B2: ZONA | C2: 1 | D2: 2 | E2: 3 | F2: 4 | G2: 5 | H2: 6 | I2: 7 | J2: 8 | K2: 9 | L2: 10 | M2: 11 | N2: 12 | O2: 13 | P2: 14 | Q2: 15 | R2: 16 | S2: 17 | T2: 18 | U2: 19 | V2: 20 | W2: 21 | X2: 22 | Y2: 23 | Z2: 24 | AA2: 25 | AB2: 26 | AC2: 27 | AD2: 28 | AE2: 29 | AF2: 30 | AG2: 31 | AH2: Enviados | AI2: Entregados por dia | AJ2: Pedidos Por dia | AK2: % Desvio | AL2: Datos pedidos 1 | AM2: Datos pedidos 2 | AN2: Faltantes a enviar | AO2: CPL | AP2: INVERSION REALIZADA | AQ2: INVERSION PENDIENTE
A3: NOVO GROUP - FIAT | B3: NACIONAL | AJ3: 25 | AL3: 100
A4: RENAULT | B4: AMBA | P4: {=TRANSPOSE(Renault!L2:L32)} -> #REF! | AH4: 19 | AI4: =AVERAGE(C4:AH4) -> #REF! | AJ4: 10 | AK4: =AI4*100/AJ4-100 -> #REF! | AL4: 20 | AN4: =AL4-AH4 -> 1
A5: GRUPO QUIJADA - PEUGEOT | B5: CORDOBA | P5: {=TRANSPOSE(Renault!L22:L39)} | AI5: =AVERAGE(C5:AG5) -> #DIV/0! | AJ5: 20 | AK5: =AI5*100/AJ5-100 -> #DIV/0! | AL5: 100 | AN5: =AL5-AH5 -> 100
A6: GRUPO QUIJADA - CITROEN | B6: AMBA | AI6: =AVERAGE(C6:AG6) -> #DIV/0! | AJ6: 20 | AK6: =AI6*100/AJ6-100 -> #DIV/0! | AL6: 100 | AN6: =AL6-AH6 -> 100
A7: CHEVROLET - ITALY | B7: PAIS | P7: {=TRANSPOSE(Chevrolet!L2:L19)} -> 17 | Q7: 28 | R7: 2 | AH7: =SUM(C7:AG7) -> 47 | AI7: =AVERAGE(C7:AH7) -> 23.5 | AJ7: 10 | AK7: =AI7*100/AJ7-100 -> 135 | AL7: 100 | AN7: =AL7-AH7 -> 53 | AO7: 1377
A8: PEUGEOT ALBENS | B8: PAIS | C8: {=TRANSPOSE(Peugeot!L27:L48)} -> 13 | D8: 34 | E8: 26 | F8: 25 | G8: 17 | H8: 20 | I8: 30 | J8: 28 | K8: 25 | L8: 22 | M8: 13 | N8: 26 | O8: 25 | P8: 19 | Q8: 2 | AH8: =SUM(C8:AG8) -> 325 | AI8: =AVERAGE(C8:AG8) -> 21.666667 | AJ8: 20 | AK8: =AI8*100/AJ8-100 -> 8.3333333 | AL8: 400 | AN8: =AL8-AH8 -> 75 | AO8: 973 | AP8: =AO8*AH8 -> 316225 | AQ8: =AN8*AO8 -> 72975
A9: FIAT AUTOS DEL SOL | B9: AMBA | C9: {=TRANSPOSE(Fiat!L20:L50)} -> 22 | D9: 25 | E9: 32 | F9: 29 | G9: 21 | H9: 39 | I9: 29 | J9: 29 | K9: 19 | L9: 38 | M9: 24 | N9: 29 | O9: 26 | P9: 33 | Q9: 45 | R9: 11 | AH9: =SUM(C9:AG9) -> 451 | AI9: =AVERAGE(C9:AG9) -> 28.1875 | AJ9: 30 | AK9: =AI9*100/AJ9-100 -> -6.0416667 | AL9: 500 | AN9: =AL9-AH9 -> 49 | AO9: 1637 | AP9: =AO9*AH9 -> 738287 | AQ9: =AN9*AO9 -> 80213
A10: TOYOTA PICHETTI | B10: AMBA | H10: {=TRANSPOSE(Toyota!L2:L25)} -> 7 | I10: 9 | J10: 7 | K10: 13 | L10: 6 | M10: 7 | N10: 8 | O10: 10 | P10: 11 | Q10: 4 | AH10: =SUM(C10:AG10) -> 82 | AI10: =AVERAGE(C10:AG10) -> 8.2 | AJ10: 10 | AK10: =AI10*100/AJ10-100 -> -18 | AL10: 100 | AN10: =AL10-AH10 -> 18 | AO10: 3358 | AP10: =AO10*AH10 -> 275356 | AQ10: =AN10*AO10 -> 60444
AH11: =SUM(AH8:AH10) -> 858 | AI11: =AVERAGE(AI8:AI10) -> 19.351389 | AJ11: =AVERAGE(AJ8:AJ10) -> 20 | AL11: =SUM(AL3:AL10) -> 1420 | AO11: =AVERAGE(AO8:AO10) -> 1989.3333 | AP11: =SUM(AP8:AP10) -> 1329868 | AQ11: =SUM(AQ8:AQ10) -> 213632
A12: 45809
A13: CLIENTE | B13: ZONA | C13: 1 | D13: 2 | E13: 3 | F13: 4 | G13: 5 | H13: 6 | I13: 7 | J13: 8 | K13: 9 | L13: 10 | M13: 11 | N13: 12 | O13: 13 | P13: 14 | Q13: 15 | R13: 16 | S13: 17 | T13: 18 | U13: 19 | V13: 20 | W13: 21 | X13: 22 | Y13: 23 | Z13: 24 | AA13: 25 | AB13: 26 | AC13: 27 | AD13: 28 | AE13: 29 | AF13: 30 | AG13: 31 | AH13: Enviados | AI13: Entregados por dia | AJ13: Por dia | AK13: % Desvio | AL13: Datos pedidos | AN13: Faltantes a enviar | AO13: CPL | AP13: INVERSION REALIZADA | AQ13: INVERSION PENDIENTE
A14: PEUGEOT ALBENS | B14: PAIS | H14: {=TRANSPOSE(Peugeot!L2:L26)} -> 15 | I14: 2 | J14: 4 | K14: 12 | L14: 1 | M14: 4 | N14: 1 | O14: 14 | P14: 10 | Q14: 8 | R14: 15 | S14: 19 | T14: 34 | U14: 26 | V14: 37 | W14: 44 | X14: 59 | Y14: 42 | Z14: 45 | AA14: 57 | AB14: 53 | AC14: 34 | AD14: 29 | AE14: 6 | AF14: 15 | AH14: =SUM(C14:AG14) -> 586 | AI14: =AVERAGE(H14:AF14) -> 23.44 | AJ14: 20 | AK14: =AI14*100/AJ14-100 -> 17.2 | AL14: 550 | AN14: =AL14-AH14 -> -36 | AO14: 1353 | AP14: =AL14*AO14 -> 744150 | AQ14: =AN14*AO14 -> -48708
A15: FIAT AUTOS DEL SOL | B15: AMBA | O15: {=TRANSPOSE(Fiat!L2:L19)} -> 1 | P15: 2 | Q15: 3 | R15: 7 | S15: 7 | T15: 23 | U15: 30 | V15: 23 | W15: 25 | X15: 43 | Y15: 34 | Z15: 38 | AA15: 50 | AB15: 58 | AC15: 45 | AD15: 39 | AE15: 9 | AF15: 16 | AH15: =SUM(C15:AG15) -> 453 | AI15: =AVERAGE(H15:AF15) -> 25.166667 | AJ15: 30 | AK15: =AI15*100/AJ15-100 -> -16.111111 | AL15: 500 | AN15: =AL15-AH15 -> 47 | AO15: 2072 | AP15: =AL15*AO15 -> 1036000 | AQ15: =AN15*AO15 -> 97384
AH16: =SUM(AH14:AH15) -> 1039 | AI16: =AVERAGE(AI13:AI15) -> 24.303333 | AJ16: =AVERAGE(AJ13:AJ15) -> 25 | AL16: =SUM(AL13:AL15) -> 1050 | AO16: =AVERAGE(AO13:AO15) -> 1712.5 | AP16: =SUM(AP13:AP15) -> 1780150 | AQ16: =SUM(AQ13:AQ15) -> 48676

Sheet Dashboard
A1: 45839
A2: CLIENTE | B2: CAMPAÑA | C2: ZONA | D2: 1 | E2: 2 | F2: 3 | G2: 4 | H2: 5 | I2: 6 | J2: 7 | K2: 8 | L2: 9 | M2: 10 | N2: 11 | O2: 12 | P2: 13 | Q2: 14 | R2: 15 | S2: 16 | T2: 17 | U2: 18 | V2: 19 | W2: 20 | X2: 21 | Y2: 22 | Z2: 23 | AA2: 24 | AB2: 25 | AC2: 26 | AD2: 27 | AE2: 28 | AF2: 29 | AG2: 30 | AH2: 31 | AI2: Enviados | AJ2: Entregados por dia | AK2: Pedidos Por dia | AL2: % Desvio | AM2: Datos pedidos 1 | AN2: Faltantes a enviar | AO2: CPL | AP2: INVERSION REALIZADA | AQ2: INVERSION PENDIENTE | AR2: INVERSION TOTAL | AS2: INVERSION TOTAL PENDIENTE
A3: A | B3: 1 | C3: NACIONAL | AM3: 100
A4: A | B4: 2 | C4: NACIONAL | AK4: 25 | AM4: 100
A5: B | B5: 1 | C5: AMBA | AJ5: 5 | AK5: 10 | AL5: =AJ5*100/AK5-100 -> -50 | AM5: 20 | AN5: =AM5-AI5 -> 20 | AO5: 2000 | AP5: =AO5*AN5 -> 40000 | AQ5: =AN5*AO5 -> 40000
A6: CLIENTE | B6: 1 | C6: CORDOBA | Q6: {=TRANSPOSE(Renault!L22:L39)} | AI6: 80 | AJ6: 5 | AK6: 20 | AL6: =AJ6*100/AK6-100 -> -75 | AM6: 100 | AN6: =AM6-AI6 -> 20 | AO6: 1000 | AP6: =AO6*AN6 -> 20000 | AQ6: =AN6*AO6 -> 20000 | AR6: =AP5+AP6 -> 60000 | AS6: =SUM(AQ5+AQ6) -> 60000
A9: Explicacion:
A10: Cliente: Nombre del cliente
A11: Campaña: numero de campaña mensual
A12: Zona: region publicitaria
A13: Dias: del 1 al 31 - se requiere contabilizar los leads diarios enviados por cliente.
A14: Enviados - este dato es tomado de planilla de cantida de leads recolectados
A15: Enviados por dia: Promedio de enviados de todo el mes
A16: Pedidos por dia: numero fijo - lo colocamos nosotros manualmente
A17: % Desvio: Pedidos por dia / Entregados por dia
A18: Datos pedidos: es la cantidad total pedida por cliente - dato manual
A19: CPL: coste por resultado - en lo posible extraerlo de meta ads. sino podems dejarlo manualmente por ahora
A20: Faltantes a enviar: Pedidos - Enviados
... A25: Promedio entregados por dia

Sheet Peugeot
A1: Fecha | B1: Nombre | C1: Telefono | D1: Localidad | E1: Modelo | F1: Horario / Comentarios | G1: ORIGEN | H1: LOCALIZACION | I1: CLIENTE | J1: Formula 1 | K1: Formula 2 | L1: Conteo de leads | M1: Fecha | N1: TOTAL LEADS
A2: 2025-06-06T12:27:03-03:00 | B2: Sin Trabajo | C2: 5491126093351 | D2: Capital | E2: 2008 | F2: Medio dia | G2: Whatsapp | H2: Pais | I2: Albens | J2: {=IF(A2:A1911="", "", DATE(LEFT(A2:A1911,4)*1, MID(A2:A1911,6,2)*1, MID(A2:A1911,9,2)*1))} -> 45814 | K2: {=UNIQUE(J2:J1911)} -> 45814 | L2: {=IF(K2:K1911="", "", COUNTIF(J2:J1911, K2:K1911))} -> 15 | M2: {=IF(K2:K1911="", "", TEXT(K2:K1911, "dd/mm/yyyy"))} -> 06/06/2025 | N2: =SUM(L2:L1911) -> 911
A3: 2025-06-06T13:17:02-03:00 | B3: Fofito | C3: 5493521408603 | D3: Dean Funes provincia de Córdoba | E3: Quisiera más info de financiaciones de Peugeot 0km | F3: Tres | G3: Whatsapp | H3: Pais | I3: Albens | J3: 45814 | K3: 45815 | L3: 2 | M3: 07/06/2025
A4: 2025-06-06T15:50:16-03:00 | B4: Monty | C4: 5493885395195 | D4: Jujuy | E4: Parnet | F4: Ahora | G4: Whatsapp | H4: Pais | I4: Albens | J4: 45814 | K4: 45816 | L4: 4 | M4: 08/06/2025
A5: 2025-06-06T15:05:42-03:00 | B5: Eduardo Cejas | C5: 5493516430233 | D5: interior | E5: 208 | F5: llamar por la tarde | G5: Whatsapp | H5: Pais | I5: Albens | J5: 45814 | K5: 45817 | L5: 12 | M5: 09/06/2025
A6: 2025-06-06T17:38:29-03:00 | B6: Ricardo Mercao Villarroel | C6: 5491158362237 | D6: interior | E6: Hola si me interesa la camioneta partner financiado en cuotas cuanto serian las cuotas x mes | F6: llamar por la tarde | G6: Whatsapp | H6: Pais | I6: Albens | J6: 45814 | K6: 45818 | L6: 1 | M6: 10/06/2025
A7: 2025-06-06T18:01:25-03:00 | B7: Victor Aquino | C7: 5493482575346 | D7: Las toscas provincia de Santa Fe. | E7: Me interesa partner. | F7: Por la mañana. | G7: Whatsapp | H7: Pais | I7: Albens | J7: 45814 | K7: 45819 | L7: 4 | M7: 11/06/2025
A8: 2025-06-06T19:49:26-03:00 | B8: Gabriel | C8: 5493434466369 | D8: Parana entre rios | E8: Parnert | F8: Dale de tarde. Después de las 17 hs | G8: Whatsapp | H8: Pais | I8: Albens | J8: 45814 | K8: 45820 | L8: 1 | M8: 12/06/2025
A9: 2025-06-06T18:54:48-03:00 | B9: Armando.C | C9: 5491137562218 | D9: interior | E9: 208 | F9: llamar por la tarde | G9: Whatsapp | H9: Pais | I9: Albens | J9: 45814 | K9: 45821 | L9: 14 | M9: 13/06/2025
A10: 2025-06-06T20:23:49-03:00 | B10: Javier Gimenez | C10: 5493644677677 | D10: Sáenz peña chaco | E10: Partner | F10: Orario comercial | G10: Whatsapp | H10: Pais | I10: Albens | J10: 45814 | K10: 45822 | L10: 10 | M10: 14/06/2025
A11: 2025-06-06T19:28:41-03:00 | B11: Jose Rivarola | C11: 5492657619845 | D11: De donde son | E11: Partner | F11: llamar por la tarde | G11: Whatsapp | H11: Pais | I11: Albens | J11: 45814 | K11: 45823 | L11: 8 | M11: 15/06/2025
A12: 2025-06-06T20:07:17-03:00 | B12: Kems Calle | C12: 5491161174239 | D12: interior | E12: 208 | F12: llamar por la tarde | G12: Whatsapp | H12: Pais | I12: Albens | J12: 45814 | K12: 45824 | L12: 15 | M12: 16/06/2025
A13: 2025-06-06T20:23:21-03:00 | B13: Osvaldo | C13: 5493858443004 | D13: interior | E13: 208 | F13: llamar por la tarde | G13: Whatsapp | H13: Pais | I13: Albens | J13: 45814 | K13: 45825 | L13: 19 | M13: 17/06/2025
A14: 2025-06-06T20:11:33-03:00 | B14: Marbel Jurado | C14: 5491157121099 | D14: interior | E14: Parner patagonia hdi | F14: llamar por la tarde | G14: Whatsapp | H14: Pais | I14: Albens | J14: 45814 | K14: 45826 | L14: 34 | M14: 18/06/2025
A15: 2025-06-06T21:59:21-03:00 | B15: Miguel Angel Piergiacomi | C15: 5492344402095 | D15: interior | E15: partner te queda patagonica | F15: llamar por la tarde | G15: Whatsapp | H15: Pais | I15: Albens | J15: 45814 | K15: 45827 | L15: 26 | M15: 19/06/2025
A16: 2025-06-06T22:05:10-03:00 | B16: Armando.C | C16: 5491137562218 | D16: interior | E16: Partner | F16: llamar por la tarde | G16: Whatsapp | H16: Pais | I16: Albens | J16: 45814 | K16: 45828 | L16: 37 | M16: 20/06/2025
A17: 2025-06-07T06:15:16-03:00 | B17: ROJITAS X SIEMPRE | C17: 5492996053450 | D17: interior | E17: 208 | F17: llamar por la tarde | G17: Whatsapp | H17: Pais | I17: Albens | J17: 45815 | K17: 45829 | L17: 44 | M17: 21/06/2025
A18: 2025-06-07T06:59:49-03:00 | B18: Oscar Gonzalez | C18: 5491157289470 | D18: interior | E18: Partner hdi vtc plus, 1.6 patagonica . | F18: llamar por la tarde | G18: Whatsapp | H18: Pais | I18: Albens | J18: 45815 | K18: 45830 | L18: 59 | M18: 22/06/2025
A19: 2025-06-08T23:19:57-03:00 | B19: eduar | C19: 5491167053821 | D19: La tablada | E19: Partner | F19: Mañana a la mañana | G19: Whatsapp | H19: Pais | I19: Albens | J19: 45816 | K19: 45831 | L19: 42 | M19: 23/06/2025
A20: 2025-06-08T23:22:38-03:00 | B20: Sergio Avalos | C20: 5491139190970 | D20: Moreno | E20: Partner | F20: 0.79166667 | G20: Whatsapp | H20: Pais | I20: Albens | J20: 45816 | K20: 45832 | L20: 45 | M20: 24/06/2025
A21: 2025-06-08T23:10:03-03:00 | B21: Javier Micucci | C21: 5492984647810 | D21: Río negro | E21: Partner | F21: llamar por la tarde | G21: Whatsapp | H21: Pais | I21: Albens | J21: 45816 | K21: 45833 | L21: 57 | M21: 25/06/2025
A22: 2025-06-08T23:12:18-03:00 | B22: CRISTIAN | C22: 5492612448795 | D22: Mendoza | E22: Partner patagonia | F22: llamar por la tarde | G22: Whatsapp | H22: Pais | I22: Albens | J22: 45816 | K22: 45834 | L22: 53 | M22: 26/06/2025
A23: 2025-06-09T09:00:24-03:00 | B23: Cutty | C23: 5493794291983 | D23: interior | E23: 208 | F23: llamar por la tarde | G23: Whatsapp | H23: Pais | I23: Albens | J23: 45817 | K23: 45835 | L23: 34 | M23: 27/06/2025
A24: 2025-06-09T16:58:22-03:00 | B24: Miguel Alfonso | C24: 5492234220500 | D24: Necesito imágenes y precio y saber donde esta para verla | E24: Me interesa la Patagonia de la imagen | F24: Mar del Plata, Provincia de Buenos Aires | G24: Whatsapp | H24: Pais | I24: Albens | J24: 45817 | K24: 45836 | L24: 29 | M24: 28/06/2025
A25: 2025-06-09T17:08:53-03:00 | B25: luisalberto | C25: 5493884726857 | D25: Jujuy | E25: Partner | F25: En la tarde estoy más libre | G25: Whatsapp | H25: Pais | I25: Albens | J25: 45817 | K25: 45837 | L25: 6 | M25: 29/06/2025
A26: 2025-06-09T19:04:56-03:00 | B26: German Mendez fernandez | C26: 5493876858786 | D26: interior | E26: 208 | F26: llamar por la tarde | G26: Whatsapp | H26: Pais | I26: Albens | J26: 45817 | K26: 45838 | L26: 15 | M26: 30/06/2025
A27: 2025-06-09T20:01:37-03:00 | B27: Juan Orlando Ruiz | C27: 5493865645090 | D27: Tucumán concepción | E27: Eso está bien | F27: Alas 12 | G27: Whatsapp | H27: Pais | I27: Albens | J27: 45817 | K27: 45839 | L27: 13 | M27: 01/07/2025
A28: 2025-06-09T19:27:33-03:00 | B28: Toti | C28: 5493704681237 | D28: Fsa capital | E28: Patagonia | F28: llamar por la tarde | G28: Whatsapp | H28: Pais | I28: Albens | J28: 45817 | K28: 45840 | L28: 34 | M28: 02/07/2025
A29: 2025-06-09T19:35:04-03:00 | B29: Miguel | C29: 5491122657044 | D29: interior | E29: 208 | F29: llamar por la tarde | G29: Whatsapp | H29: Pais | I29: Albens | J29: 45817 | K29: 45841 | L29: 26 | M29: 03/07/2025
A30: 2025-06-09T20:36:44-03:00 | B30: Adrian | C30: 5492216047542 | D30: Bs as(la plata) | E30: Partner | F30: llamar por la tarde | G30: Whatsapp | H30: Pais | I30: Albens | J30: 45817 | K30: 45842 | L30: 25 | M30: 04/07/2025
A31: 2025-06-09T20:43:34-03:00 | B31: Edgar Alonso | C31: 5491135911706 | D31: interior | E31: De cuanto cuotas estamos hablando | F31: llamar por la tarde | G31: Whatsapp | H31: Pais | I31: Albens | J31: 45817 | K31: 45843 | L31: 17 | M31: 05/07/2025
A32: 2025-06-09T21:50:13-03:00 | B32: Diego | C32: 5491164734259 | D32: Zona norte jcpaz | E32: Partner | F32: Entre las 16 y 16 30 | G32: Whatsapp | H32: Pais | I32: Albens | J32: 45817 | K32: 45844 | L32: 20 | M32: 06/07/2025
A33: 2025-06-09T21:00:57-03:00 | B33: Víctor | C33: 5493704585688 | D33: interior | E33: 208 | F33: llamar por la tarde | G33: Whatsapp | H33: Pais | I33: Albens | J33: 45817 | K33: 45845 | L33: 30 | M33: 07/07/2025
A34: 2025-06-09T21:23:38-03:00 | B34: Hugo Nuñez | C34: 5491123084854 | D34: interior | E34: 208 | F34: llamar por la tarde | G34: Whatsapp | H34: Pais | I34: Albens | J34: 45817 | K34: 45846 | L34: 28 | M34: 08/07/2025
A35: 2025-06-10T13:45:31-03:00 | B35: Seba | C35: 5492345441872 | D35: Partner | E35: Me pasa indo | F35: 45802 | G35: Whatsapp | H35: Pais | I35: Albens | J35: 45818 | K35: 45847 | L35: 25 | M35: 09/07/2025
A36: 2025-06-11T00:06:50-03:00 | B36: Leonel Ataliva | C36: 5491171681886 | D36: Buenos Aires Quilmes | E36: Partner | F36: Hola quería dar un anticipo y el resto en cuotas | G36: Whatsapp | H36: Pais | I36: Albens | J36: 45819 | K36: 45848 | L36: 22 | M36: 10/07/2025
A37: 2025-06-11T00:25:06-03:00 | B37: Javier Perez | C37: 5492227510232 | D37: Buenos Aires | E37: Partner | F37: Cualquier horario | G37: Whatsapp | H37: Pais | I37: Albens | J37: 45819 | K37: 45849 | L37: 13 | M37: 11/07/2025
A38: 2025-06-11T00:46:11-03:00 | B38: . | C38: 5493854111727 | D38: Santiago del estero | E38: Partner | F38: 10 am | G38: Whatsapp | H38: Pais | I38: Albens | J38: 45819 | K38: 45850 | L38: 26 | M38: 12/07/2025
A39: 2025-06-11T18:29:45-03:00 | B39: Seba | C39: 5492345441872 | D39: Y no me respondiste | E39: Ya te pregunte | F39: llamar por la tarde | G39: Whatsapp | H39: Pais | I39: Albens | J39: 45819 | K39: 45851 | L39: 25 | M39: 13/07/2025
A40: 2025-06-12T23:22:52-03:00 | B40: Juan Santos Márquez | C40: 5492634558126 | D40: Soy de san Martín | E40: Pagner | F40: 10 de la mañana | G40: Whatsapp | H40: Pais | I40: Albens | J40: 45820 | K40: 45852 | L40: 19 | M40: 14/07/2025
A41: 2025-06-13T07:56:10-03:00 | B41: Gabriel Alexandro Paredes | C41: 5492214558932 | D41: Berisso.. la plata | E41: Parnert patagónica | F41: llamar por la tarde | G41: Whatsapp | H41: Pais | I41: Albens | J41: 45821 | K41: 45854 | L41: 2 | M41: 16/07/2025
A42: 2025-06-13T10:32:26-03:00 | B42: C.A | C42: 5491125583498 | D42: General Rodríguez zona oeste | E42: 208 | F42: Después de las 15 hs | G42: Whatsapp | H42: Pais | I42: Albens | J42: 45821
A43: 2025-06-13T09:53:03-03:00 | B43: Ernesto | C43: 5493426148141 | D43: interior | E43: Parnert! | F43: llamar por la tarde | G43: Whatsapp | H43: Pais | I43: Albens | J43: 45821
A44: 2025-06-13T13:09:38-03:00 | B44: Lolo | C44: 5491131456617 | D44: 45901 | E44: Tengo parnet 2008 | F44: Disel | G44: Whatsapp | H44: Pais | I44: Albens | J44: 45821
A45: 2025-06-13T14:09:07-03:00 | B45: Siul 🥷🏻 | C45: 5491134023609 | D45: Rafael Castillo | E45: Peugeot parnet mixto | F45: Alas 5:30 | G45: Whatsapp | H45: Pais | I45: Albens | J45: 45821
A46: 2025-06-13T13:15:05-03:00 | B46: Nicasio | C46: 5492494337901 | D46: interior | E46: 208 | F46: llamar por la tarde | G46: Whatsapp | H46: Pais | I46: Albens | J46: 45821
A47: 2025-06-13T16:40:37-03:00 | B47: Soledad Bobadilla | C47: 5492942692535 | D47: interior | E47: 208 | F47: llamar por la tarde | G47: Whatsapp | H47: Pais | I47: Albens | J47: 45821
A48: 2025-06-13T19:24:15-03:00 | B48: Ernesto Melgarejo | C48: 5493725548222 | D48: Resistencia chacó | E48: Patnner | F48: X la mañana | G48: Whatsapp | H48: Pais | I48: Albens | J48: 45821
A49: 2025-06-13T18:34:22-03:00 | B49: Blas | C49: 5491133561036 | D49: interior | E49: 208 | F49: llamar por la tarde | G49: Whatsapp | H49: Pais | I49: Albens | J49: 45821
A50: 2025-06-13T18:53:58-03:00 | B50: José Moyano | C50: 5493549465008 | D50: interior | E50: 208 | F50: llamar por la tarde | G50: Whatsapp | H50: Pais | I50: Albens | J50: 45821
A51: 2025-06-13T20:19:48-03:00 | B51: Amo Mi Familia 🥰😍 | C51: 5491144120028 | D51: Vivo en virrey del pino | E51: Buenas tardes partner | F51: En cualquier horario | G51: Whatsapp | H51: Pais | I51: Albens | J51: 45821
A52: 2025-06-13T20:19:55-03:00 | B52: Miguel | C52: 5493412826202 | D52: interior | E52: Partner | F52: llamar por la tarde | G52: Whatsapp | H52: Pais | I52: Albens | J52: 45821
A53: 2025-06-13T22:34:40-03:00 | B53: Marcelo Antonio | C53: 5493436215951 | D53: interior | E53: 208 | F53: llamar por la tarde | G53: Whatsapp | H53: Pais | I53: Albens | J53: 45821
A54: 2025-06-13T23:49:25-03:00 | B54: Estela Azucena Arrieta | C54: 5493878398637 | D54: interior | E54: 208 | F54: llamar por la tarde | G54: Whatsapp | H54: Pais | I54: Albens | J54: 45821
A55: 2025-06-14T00:51:42-03:00 | B55: Alejandro | C55: 5493585764294 | D55: interior | E55: 208 | F55: llamar por la tarde | G55: Whatsapp | H55: Pais | I55: Albens | J55: 45822
A56: 2025-06-14T14:20:52-03:00 | B56: Dante 😁 | C56: 5492284687055 | D56: Olavarría | E56: Partner patagónica | F56: Cualquier horario | G56: Whatsapp | H56: Pais | I56: Albens | J56: 45822
A57: 2025-06-14T17:13:10-03:00 | B57: yhandeli.Meli | C57: 5491164944195 | D57: En cañuelas | E57: Cuánto está el precio patagónica vtc plus | F57: Ay en estok | G57: Whatsapp | H57: Pais | I57: Albens | J57: 45822
A58: 2025-06-14T17:50:19-03:00 | B58: Daniel | C58: 5491140852535 | D58: Capital | E58: Parnet | F58: Lugano | G58: Whatsapp | H58: Pais | I58: Albens | J58: 45822
A59: 2025-06-14T17:12:12-03:00 | B59: Robert Vz | C59: 5491130381469 | D59: interior | E59: 208 | F59: llamar por la tarde | G59: Whatsapp | H59: Pais | I59: Albens | J59: 45822
A60: 2025-06-14T19:56:26-03:00 | B60: L.A.M. | C60: 5491125193731 | D60: Merlo | E60: 208 | F60: Buenos aires | G60: Whatsapp | H60: Pais | I60: Albens | J60: 45822
A61: 2025-06-14T19:19:27-03:00 | B61: Distribuidora De Sandra M | C61: 5492995970518 | D61: interior | E61: 208 | F61: llamar por la tarde | G61: Whatsapp | H61: Pais | I61: Albens | J61: 45822
A62: 2025-06-14T18:43:09-03:00 | B62: BDR AUTOMOTORES | C62: 5491165631622 | D62: interior | E62: Partner | F62: llamar por la tarde | G62: Whatsapp | H62: Pais | I62: Albens | J62: 45822
A63: 2025-06-14T22:03:46-03:00 | B63: Gracias Xest C Mis Hijos | C63: 5492622418066 | D63: Mendoza | E63: Partner | F63: Tengo una kangoo 2012turbo Diesel full1.5 | G63: Whatsapp | H63: Pais | I63: Albens | J63: 45822
A64: 2025-06-14T22:00:04-03:00 | B64: Graciela | C64: 5493751232251 | D64: interior | E64: 208 | F64: llamar por la tarde | G64: Whatsapp | H64: Pais | I64: Albens | J64: 45822
A65: 2025-06-15T15:41:03-03:00 | B65: Jorge Barria | C65: 5492996740558 | D65: interior | E65: 208 | F65: llamar por la tarde | G65: Whatsapp | H65: Pais | I65: Albens | J65: 45823
A66: 2025-06-15T16:53:18-03:00 | B66: David | C66: 5492617149985 | D66: Mendoza... | E66: Buenas tardes..si me puede dar opciones.. | F66: De lunes a viernes de 12hs a 13hs y de 19hs en adelante... | G66: Whatsapp | H66: Pais | I66: Albens | J66: 45823
A67: 2025-06-15T16:42:29-03:00 | B67: benja | C67: 5492617488198 | D67: interior | E67: Hola mi amor te | F67: llamar por la tarde | G67: Whatsapp | H67: Pais | I67: Albens | J67: 45823
A68: 2025-06-15T18:15:50-03:00 | B68: Yesi | C68: 5492615450599 | D68: Mendoza | E68: Cuanto es el anticipo para retirar | F68: En cualquier momento | G68: Whatsapp | H68: Pais | I68: Albens | J68: 45823
A69: 2025-06-15T18:31:47-03:00 | B69: Tommy Aratin | C69: 5491134581398 | D69: Lanus | E69: Partner | F69: Después de las 17hrs de lunes a viernes o desde las 10 de la mañana sábado y domingo y feriados | G69: Whatsapp | H69: Pais | I69: Albens | J69: 45823
A70: 2025-06-15T18:16:37-03:00 | B70: David | C70: 5492214940801 | D70: interior | E70: 208 | F70: llamar por la tarde | G70: Whatsapp | H70: Pais | I70: Albens | J70: 45823
A71: 2025-06-15T18:31:32-03:00 | B71: Fani | C71: 5493704825014 | D71: interior | E71: 208 | F71: llamar por la tarde | G71: Whatsapp | H71: Pais | I71: Albens | J71: 45823
A72: 2025-06-15T20:12:31-03:00 | B72: sergio | C72: 5493516168291 | D72: interior | E72: 208 | F72: llamar por la tarde | G72: Whatsapp | H72: Pais | I72: Albens | J72: 45823
A73: 2025-06-16T13:01:34-03:00 | B73: Cesar | C73: 5491158497290 | D73: interior | E73: 208 | F73: llamar por la tarde | G73: Whatsapp | H73: Pais | I73: Albens | J73: 45824
A74: 2025-06-16T14:32:45-03:00 | B74: Juan de dios Tello | C74: 5492613027548 | D74: Mendoza | E74: 208 | F74: De 18.horas en adelante | G74: Whatsapp | H74: Pais | I74: Albens | J74: 45824
A75: 2025-06-16T13:38:52-03:00 | B75: Julio Ariel Machuca | C75: 5493624038664 | D75: interior | E75: 208 | F75: llamar por la tarde | G75: Whatsapp | H75: Pais | I75: Albens | J75: 45824
A76: 2025-06-16T15:19:12-03:00 | B76: Nancy | C76: 5492622247055 | D76: Mendoza | E76: Partner patagonica | F76: Me encanta y quier canbiar la que ya tengo | G76: Whatsapp | H76: Pais | I76: Albens | J76: 45824
A77: 2025-06-16T16:17:05-03:00 | B77: Roberto | C77: 5493777237270 | D77: CORRIENTES | E77: Patner Patagonica Diésel | F77: Tengo comercio | G77: Whatsapp | H77: Pais | I77: Albens | J77: 45824
A78: 2025-06-16T15:37:07-03:00 | B78: Mónica | C78: 5492323317141 | D78: interior | E78: 208 | F78: llamar por la tarde | G78: Whatsapp | H78: Pais | I78: Albens | J78: 45824
A79: 2025-06-16T16:53:08-03:00 | B79: Fabian Rogel | C79: 5493434065968 | D79: interior | E79: 208 | F79: llamar por la tarde | G79: Whatsapp | H79: Pais | I79: Albens | J79: 45824
A80: 2025-06-16T17:19:27-03:00 | B80: Gena Mamani | C80: 5492266470490 | D80: interior | E80: En qué zona de Capital federal se encuentran gracias | F80: llamar por la tarde | G80: Whatsapp | H80: Pais | I80: Albens | J80: 45824
A81: 2025-06-16T18:17:00-03:00 | B81: Miguel | C81: 5492995737710 | D81: Mza | E81: Partner patag hdi | F81: llamar por la tarde | G81: Whatsapp | H81: Pais | I81: Albens | J81: 45824
A82: 2025-06-16T18:40:34-03:00 | B82: Rodrigo Martinez | C82: 5492616610366 | D82: Mendoza | E82: Partner | F82: De 8 a 13 hs | G82: Whatsapp | H82: Pais | I82: Albens | J82: 45824
A83: 2025-06-16T19:51:39-03:00 | B83: Luciano Flocco | C83: 5493456439231 | D83: interior | E83: Partner | F83: llamar por la tarde | G83: Whatsapp | H83: Pais | I83: Albens | J83: 45824
A84: 2025-06-16T20:55:13-03:00 | B84: alberto hugo bazan | C84: 5492804953805 | D84: interior | E84: 208 | F84: llamar por la tarde | G84: Whatsapp | H84: Pais | I84: Albens | J84: 45824
A85: 2025-06-16T20:59:37-03:00 | B85: Jefe Registro Civil Fortín Lavalle | C85: 5493644187099 | D85: interior | E85: 208 | F85: llamar por la tarde | G85: Whatsapp | H85: Pais | I85: Albens | J85: 45824
A86: 2025-06-16T21:04:08-03:00 | B86: Eduardo | C86: 5491121761024 | D86: interior | E86: 208 | F86: llamar por la tarde | G86: Whatsapp | H86: Pais | I86: Albens | J86: 45824
A87: 2025-06-16T21:18:42-03:00 | B87: CEO | C87: 5493764683943 | D87: Caba | E87: Hola.. cual es el Minimo Anticipo? | F87: llamar por la tarde | G87: Whatsapp | H87: Pais | I87: Albens | J87: 45824
A88: 2025-06-17T12:59:00-03:00 | B88: miguel alonso | C88: 5491151576090 | D88: En lomas de zamora | E88: Patner | F88: La patner patagonica tienen disponibles | G88: Whatsapp | H88: Pais | I88: Albens | J88: 45825
A89: 2025-06-17T13:05:48-03:00 | B89: Feliciano Rivera | C89: 5492216059865 | D89: Pasame un teléfono | E89: Peugeot patagonia tenes2019a2021 | F89: Nafta | G89: Whatsapp | H89: Pais | I89: Albens | J89: 45825
A90: 2025-06-17T13:38:15-03:00 | B90: Mayra Galindez | C90: 5493573463566 | D90: Córdoba | E90: Partner | F90: 19 | G90: Whatsapp | H90: Pais | I90: Albens | J90: 45825
A91: 2025-06-17T12:43:19-03:00 | B91: Nancy | C91: 5491158321588 | D91: interior | E91: De dónde son? | F91: llamar por la tarde | G91: Whatsapp | H91: Pais | I91: Albens | J91: 45825
A92: 2025-06-17T13:38:55-03:00 | B92: Mario | C92: 5492942597969 | D92: interior | E92: 208 | F92: llamar por la tarde | G92: Whatsapp | H92: Pais | I92: Albens | J92: 45825
A93: 2025-06-17T13:57:15-03:00 | B93: Maria Katana Lanza | C93: 5493487693472 | D93: interior | E93: 208 | F93: llamar por la tarde | G93: Whatsapp | H93: Pais | I93: Albens | J93: 45825
A94: 2025-06-17T15:14:43-03:00 | B94: Bachi | C94: 5491133650540 | D94: Bs as | E94: Parrner | F94: Ahora Estoi libre | G94: Whatsapp | H94: Pais | I94: Albens | J94: 45825
A95: 2025-06-17T14:29:13-03:00 | B95: Maria 🤍 | C95: 5493562445716 | D95: interior | E95: 208 | F95: llamar por la tarde | G95: Whatsapp | H95: Pais | I95: Albens | J95: 45825
A96: 2025-06-17T14:58:38-03:00 | B96: Luis Taipe | C96: 5491163036131 | D96: Lomas del mirador | E96: Hola buenas tardes | F96: Buscó peugeot partner patagonico nafta | G96: Whatsapp | H96: Pais | I96: Albens | J96: 45825
A97: 2025-06-17T14:16:37-03:00 | B97: Lobo Saa | C97: 5491126569581 | D97: Buenos Aires, La matanza González catan | E97: Otro | F97: llamar por la tarde | G97: Whatsapp | H97: Pais | I97: Albens | J97: 45825
A98: 2025-06-17T14:40:07-03:00 | B98: Sebastian | C98: 5493413420126 | D98: interior | E98: 208 | F98: llamar por la tarde | G98: Whatsapp | H98: Pais | I98: Albens | J98: 45825
A99: 2025-06-17T14:41:10-03:00 | B99: Jose Mario | C99: 5493546544966 | D99: interior | E99: 208 | F99: llamar por la tarde | G99: Whatsapp | H99: Pais | I99: Albens | J99: 45825
A100: 2025-06-17T14:43:00-03:00 | B100: Gustavo Diaz | C100: 5492645811366 | D100: interior | E100: 208 | F100: llamar por la tarde | G100: Whatsapp | H100: Pais | I100: Albens | J100: 45825
...

Sheet Fiat
A1: Fecha | B1: Nombre | C1: Telefono | D1: Localidad | E1: Modelo | F1: Horario / Comentarios | G1: ORIGEN | H1: LOCALIZACION | I1: CLIENTE | J1: Formula 1 | K1: Formula 2 | L1: Conteo de leads | M1: Fecha | N1: TOTAL LEADS
A2: 2025-06-13T17:07:48-03:00 | B2: Celestina | C2: 5491160502851 | D2: amba | E2: Cómo es la entrega y que requisitos | F2: llamar por la tarde | G2: Whatsapp | H2: Amba | I2: Autos del Sol | J2: {=IF(A2:A2005="", "", DATE(LEFT(A2:A2005,4)*1, MID(A2:A2005,6,2)*1, MID(A2:A2005,9,2)*1))} -> 45821 | K2: {=UNIQUE(J2:J2005)} -> 45821 | L2: {=IF(K2:K2005="", "", COUNTIF(J2:J2005, K2:K2005))} -> 1 | M2: {=IF(K2:K2005="", "", TEXT(K2:K2005, "dd/mm/yyyy"))} -> 13/06/2025 | N2: =SUM(L2:L2005) -> 904
A3: 2025-06-14T09:18:36-03:00 | B3: Cristo X Siempre | C3: 5491133727352 | D3: amba | E3: Cronos | F3: llamar por la tarde | G3: Whatsapp | H3: Amba | I3: Autos del Sol | J3: 45822 | K3: 45822 | L3: 2 | M3: 14/06/2025
A4: 2025-06-14T17:00:49-03:00 | B4: HUMBERTO WALTER CINCO | C4: 5491139286350 | D4: En TORTUGUITA | E4: CRONOS | F4: MAÑANA A LAS 10 X FAVOR GRACIAS | G4: Whatsapp | H4: Amba | I4: Autos del Sol | J4: 45822 | K4: 45823 | L4: 3 | M4: 15/06/2025
A5: 2025-06-15T18:58:36-03:00 | B5: More | C5: 5491166899803 | D5: amba | E5: Cronos | F5: llamar por la tarde | G5: Whatsapp | H5: Amba | I5: Autos del Sol | J5: 45823 | K5: 45824 | L5: 7 | M5: 16/06/2025
A6: 2025-06-15T20:21:32-03:00 | B6: Don Lippo | C6: 5491126506666 | D6: Avellaneda | E6: Cronos | F6: Ahora | G6: Whatsapp | H6: Amba | I6: Autos del Sol | J6: 45823 | K6: 45825 | L6: 7 | M6: 17/06/2025
A7: 2025-06-15T20:51:04-03:00 | B7: Gustavo | C7: 5491151372553 | D7: Caba vlla urquiza | E7: Cronos | F7: A paetir 10 de la mañana | G7: Whatsapp | H7: Amba | I7: Autos del Sol | J7: 45823 | K7: 45826 | L7: 23 | M7: 18/06/2025
A8: 2025-06-16T13:03:05-03:00 | B8: marce | C8: 5491138087112 | D8: San Martín | E8: Okey | F8: En cualquier horrio | G8: Whatsapp | H8: Amba | I8: Autos del Sol | J8: 45824 | K8: 45827 | L8: 30 | M8: 19/06/2025
A9: 2025-06-16T14:25:28-03:00 | B9: Marcelo Lizarraga | C9: 5491153388260 | D9: Tristán Suárez | E9: Cronos | F9: X la tarde | G9: Whatsapp | H9: Amba | I9: Autos del Sol | J9: 45824 | K9: 45828 | L9: 23 | M9: 20/06/2025
A10: 2025-06-16T15:48:49-03:00 | B10: Cheke Seoane 👑 | C10: 5491150516448 | D10: Villa Lugano CABA | E10: Cronos | F10: Me gustaría sacar un Fiat para poder trabajar en aplicación | G10: Whatsapp | H10: Amba | I10: Autos del Sol | J10: 45824 | K10: 45829 | L10: 25 | M10: 21/06/2025
A11: 2025-06-16T16:00:37-03:00 | B11: Amanda Villaruel | C11: 5491134757144 | D11: amba | E11: Cronos | F11: llamar por la tarde | G11: Whatsapp | H11: Amba | I11: Autos del Sol | J11: 45824 | K11: 45830 | L11: 43 | M11: 22/06/2025
A12: 2025-06-16T16:04:38-03:00 | B12: Emilio | C12: 5491130269840 | D12: amba | E12: Cronos | F12: llamar por la tarde | G12: Whatsapp | H12: Amba | I12: Autos del Sol | J12: 45824 | K12: 45831 | L12: 34 | M12: 23/06/2025
A13: 2025-06-16T17:27:26-03:00 | B13: Rosa 🌹 | C13: 5491125907500 | D13: Capital flores | E13: Cronos | F13: Por la tarde tipo 3 adelante gracias | G13: Whatsapp | H13: Amba | I13: Autos del Sol | J13: 45824 | K13: 45832 | L13: 38 | M13: 24/06/2025
A14: 2025-06-16T18:43:55-03:00 | B14: Ismael | C14: 5491141754237 | D14: Ok | E14: Necesito un autochico para mi soy jubilado | F14: Yo estoy | G14: Whatsapp | H14: Amba | I14: Autos del Sol | J14: 45824 | K14: 45833 | L14: 50 | M14: 25/06/2025
... A35: 2025-06-18T19:07:28-03:00 | B35: Rolando | C35: 5491134983585 | D35: Caba | E35: Cronos | F35: llamar por la tarde | G35: Whatsapp | H35: Amba | I35: Autos del Sol | J35: 45826 | K35: 45854 | L35: 11 | M35: 16/07/2025
A36: 2025-06-18T20:19:26-03:00 | B36: ⚽ | C36: 5491171296429 | D36: San Miguel | E36: Cronos | F36: Mañana | G36: Whatsapp | H36: Amba | I36: Autos del Sol | J36: 45826
A37: 2025-06-18T20:29:31-03:00 | B37: El Chuky Antoniotti | C37: 5491149145392 | D37: Norte tigre | E37: Crono | F37: De11 a15 | G37: Whatsapp | H37: Amba | I37: Autos del Sol | J37: 45826
A38: 2025-06-18T20:30:00-03:00 | B38: El Tano | C38: 5491140822835 | D38: amba | E38: Cronos | F38: llamar por la tarde | G38: Whatsapp | H38: Amba | I38: Autos del Sol | J38: 45826
A39: 2025-06-18T20:32:13-03:00 | B39: 🌳🛖🌳🌳🔥🏡🔥🌳🌳🏢🌳 | C39: 5491135204129 | D39: amba | E39: Cronos | F39: llamar por la tarde | G39: Whatsapp | H39: Amba | I39: Autos del Sol | J39: 45826
A40: 2025-06-18T21:05:45-03:00 | B40: hugoalfaro258 | C40: 5491137931252 | D40: amba | E40: Cronos | F40: llamar por la tarde | G40: Whatsapp | H40: Amba | I40: Autos del Sol | J40: 45826
A41: 2025-06-18T21:36:24-03:00 | B41: 🫣 | C41: 5491134153064 | D41: amba | E41: Cronos | F41: llamar por la tarde | G41: Whatsapp | H41: Amba | I41: Autos del Sol | J41: 45826
A42: 2025-06-18T21:37:36-03:00 | B42: Carlos | C42: 5491168063570 | D42: amba | E42: Crono | F42: llamar por la tarde | G42: Whatsapp | H42: Amba | I42: Autos del Sol | J42: 45826
A43: 2025-06-18T21:51:54-03:00 | B43: Dario Juarez | C43: 5491154173644 | D43: amba | E43: Cronos | F43: llamar por la tarde | G43: Whatsapp | H43: Amba | I43: Autos del Sol | J43: 45826
A44: 2025-06-18T23:17:25-03:00 | B44: Eduardo | C44: 5491138768606 | D44: amba | E44: Cronos | F44: llamar por la tarde | G44: Whatsapp | H44: Amba | I44: Autos del Sol | J44: 45826
A45: 2025-06-19T01:40:57-03:00 | B45: Sebastian Galeano | C45: 5491122931813 | D45: Bueno... Solo watsap.... Para que me quede todo... Puede ser?? | E45: Hola... Estoy interesado por el Cronos... | F45: A la hora que sea.. pero solo watsap... | G45: Whatsapp | H45: Amba | I45: Autos del Sol | J45: 45827
A46: 2025-06-19T07:45:14-03:00 | B46: Mathias | C46: 59899142385 | D46: Vivo en cápital Liniers | E46: Arco | F46: Al medio día puede ser | G46: Whatsapp | H46: Amba | I46: Autos del Sol | J46: 45827
A47: 2025-06-19T07:20:15-03:00 | B47: Beto | C47: 5491133927052 | D47: amba | E47: Cronos | F47: llamar por la tarde | G47: Whatsapp | H47: Amba | I47: Autos del Sol | J47: 45827
... A231: 2025-06-24T21:50:04-03:00 | B231: Amor del bueno 💙💛💙 | C231: 5491150240171 | D231: En gregorio de Laferrere | E231: Cronos | F231: De 12 a 12:40 o después de las 17 | G231: Whatsapp | H231: Amba | I231: Autos del Sol | J231: 45832
A232: 2025-06-24T22:14:02-03:00 | B232: 3755384888 | C232: 5493755384888 | D232: Soy de lomas de zamora | E232: El más económico | F232: Buenos aire | G232: Whatsapp | H232: Amba | I232: Autos del Sol | J232: 45832
A233: 2025-06-24T21:27:15-03:00 | B233: Tda La Vida LOMAS 🇦🇹⚔️🇦🇹 | C233: 5491125027028 | D233: amba | E233: Cronos | F233: llamar por la tarde | G233: Whatsapp | H233: Amba | I233: Autos del Sol | J233: 45832
A234: 2025-06-24T22:16:44-03:00 | B234: 😕 | C234: 5491149705386 | D234: amba | E234: Cronos | F234: llamar por la tarde | G234: Whatsapp | H234: Amba | I234: Autos del Sol | J234: 45832
A235: 2025-06-24T22:19:41-03:00 | B235: Richard | C235: 5491134618809 | D235: Banfield | E235: Cronos | F235: llamar por la tarde | G235: Whatsapp | H235: Amba | I235: Autos del Sol | J235: 45832
A236: 2025-06-24T22:29:37-03:00 | B236: Mario Campos | C236: 5491154125578 | D236: Pablo nogues | E236: Mobi | F236: llamar por la tarde | G236: Whatsapp | H236: Amba | I236: Autos del Sol | J236: 45832
A237: 2025-06-24T22:57:07-03:00 | B237: Marcelo🤑🤑 | C237: 5491149705779 | D237: amba | E237: Cronos | F237: llamar por la tarde | G237: Whatsapp | H237: Amba | I237: Autos del Sol | J237: 45832
A238: 2025-06-25T00:16:08-03:00 | B238: lautygt32 | C238: 5491128750358 | D238: Gregorio laferrere | E238: Cronos | F238: llamar por la tarde | G238: Whatsapp | H238: Amba | I238: Autos del Sol | J238: 45833
A239: 2025-06-25T01:35:08-03:00 | B239: Bienestar y servicio | C239: 5493872280342 | D239: amba | E239: Cronos | F239: llamar por la tarde | G239: Whatsapp | H239: Amba | I239: Autos del Sol | J239: 45833
A240: 2025-06-25T04:53:28-03:00 | B240: Tortu | C240: 5491165174482 | D240: amba | E240: Cronos | F240: llamar por la tarde | G240: Whatsapp | H240: Amba | I240: Autos del Sol | J240: 45833
A241: 2025-06-25T06:36:12-03:00 | B241: Cecilia Gonzalez | C241: 5491156014016 | D241: amba | E241: Cronos | F241: llamar por la tarde | G241: Whatsapp | H241: Amba | I241: Autos del Sol | J241: 45833
A242: 2025-06-25T11:12:04-03:00 | B242: Lucas Torres | C242: 5491136848993 | D242: Vicente López | E242: El más económico | F242: X wh8 | G242: Whatsapp | H242: Amba | I242: Autos del Sol | J242: 45833
A243: 2025-06-25T11:52:05-03:00 | B243: Eze | C243: 5491131678125 | D243: Laferrere | E243: Otro | F243: Todo el día solo x vía WhatsApp | G243: Whatsapp | H243: Amba | I243: Autos del Sol | J243: 45833
A244: 2025-06-25T12:01:22-03:00 | B244: 🚗 | C244: 595987246400 | D244: Sou emanuel | E244: Cronos | F244: Ramirez | G244: Whatsapp | H244: Amba | I244: Autos del Sol | J244: 45833
... A289: 2025-06-26T00:14:59-03:00 | B289: María Ines | C289: 5491138689123 | D289: amba | E289: Cronos | F289: llamar por la tarde | G289: Whatsapp | H289: Amba | I289: Autos del Sol | J289: 45834
A290: 2025-06-26T01:48:08-03:00 | B290: Ezquiel👺👹 | C290: 5491135742095 | D290: Dni | E290: Hola | F290: 47653415 | G290: Whatsapp | H290: Amba | I290: Autos del Sol | J290: 45834
A291: 2025-06-26T01:01:11-03:00 | B291: Gustavo | C291: 5491159221071 | D291: amba | E291: Cronos | F291: llamar por la tarde | G291: Whatsapp | H291: Amba | I291: Autos del Sol | J291: 45834
A292: 2025-06-26T02:35:10-03:00 | B292: Angel | C292: 5491155722177 | D292: amba | E292: Cronos | F292: llamar por la tarde | G292: Whatsapp | H292: Amba | I292: Autos del Sol | J292: 45834
A293: 2025-06-26T04:29:39-03:00 | B293: Alfredo Fereira | C293: 5493756644367 | D293: amba | E293: Cronos | F293: llamar por la tarde | G293: Whatsapp | H293: Amba | I293: Autos del Sol | J293: 45834
A294: 2025-06-26T05:32:02-03:00 | B294: Tomas Neiser Hernan Manco | C294: 5491131322046 | D294: amba | E294: Cronos | F294: llamar por la tarde | G294: Whatsapp | H294: Amba | I294: Autos del Sol | J294: 45834
A295: 2025-06-26T05:52:20-03:00 | B295: 🙏Pedro | C295: 5491138790724 | D295: amba | E295: Cronos | F295: llamar por la tarde | G295: Whatsapp | H295: Amba | I295: Autos del Sol | J295: 45834
A296: 2025-06-26T06:36:40-03:00 | B296: Roberto cruz te amo 🥰😍😘💛💙 | C296: 5491123239771 | D296: amba | E296: Cronos | F296: llamar por la tarde | G296: Whatsapp | H296: Amba | I296: Autos del Sol | J296: 45834
A297: 2025-06-26T08:20:03-03:00 | B297: . | C297: 5491141917651 | D297: Caba | E297: Cronos | F297: Queria saber como ago para retirar con dni | G297: Whatsapp | H297: Amba | I297: Autos del Sol | J297: 45834
A298: 2025-06-26T07:48:08-03:00 | B298: 🌳🛖🌳🌳🔥🏡🔥🌳🌳🏢🌳 | C298: 5491135204129 | D298: amba | E298: Cronos | F298: llamar por la tarde | G298: Whatsapp | H298: Amba | I298: Autos del Sol | J298: 45834
A299: 2025-06-26T09:15:10-03:00 | B299: Oscar Herrera | C299: 5491161551015 | D299: Capital federal | E299: Otro | F299: Ahora q estoy libre | G299: Whatsapp | H299: Amba | I299: Autos del Sol | J299: 45834
A300: 2025-06-26T08:18:03-03:00 | B300: p£D?0 ●<@mP◇ | C300: 5491165750256 | D300: amba | E300: Cronos | F300: llamar por la tarde | G300: Whatsapp | H300: Amba | I300: Autos del Sol | J300: 45834
A301: 2025-06-26T08:44:48-03:00 | B301: Saúl Morales | C301: 5491134650561 | D301: amba | E301: Cronos | F301: llamar por la tarde | G301: Whatsapp | H301: Amba | I301: Autos del Sol | J301: 45834
A302: 2025-06-26T09:02:10-03:00 | B302: skibidi diana | C302: 5491170600494 | D302: amba | E302: Cronos | F302: llamar por la tarde | G302: Whatsapp | H302: Amba | I302: Autos del Sol | J302: 45834
... A313: 2025-06-26T13:10:52-03:00 | B313: Miguel Argañaraz🐴 | C313: 5491164463316 | D313: Escobar | E313: Strada | F313: llamar por la tarde | G313: Whatsapp | H313: Amba | I313: Autos del Sol | J313: 45834
A314: 2025-06-26T14:09:51-03:00 | B314: Gaston Llopart | C314: 5491127607557 | E314: Fiat cronos | F314: Contéstame lo que te pregunto gracias | G314: Whatsapp | H314: Amba | I314: Autos del Sol | J314: 45834
A315: 2025-06-26T17:28:30-03:00 | B315: Cecilia 🌺🌺🌺 | C315: 5491121581816 | D315: Donde esta el local y como se llama la agencia | E315: Dk de esta la agencia | F315: No quiere un asesor yo quiero ir a la agencia | G315: Whatsapp | H315: Amba | I315: Autos del Sol | J315: 45834
A316: 2025-06-26T17:31:16-03:00 | B316: José Castillo | C316: 5493704955745 | D316: Formosa Ctal | E316: Strada en cuota tengo una Toro Mod 2017 | F316: Hora dose a diesisei | G316: Whatsapp | H316: Amba | I316: Autos del Sol | J316: 45834
A317: 2025-06-26T17:35:08-03:00 | B317: Walter Mancera | C317: 5491138015982 | D317: Ezeiza | E317: Cronos | F317: Vía escrita en cualquier horario llamadas después de las 22 pero que me contacte x escrito primero | G317: Whatsapp | H317: Amba | I317: Autos del Sol | J317: 45834
A318: 2025-06-26T17:30:43-03:00 | B318: Segundo Acosta | C318: 5493644225323 | D318: Q es plan si es plan no m interesa | E318: Tengo una dueter 2015 cn 130 mil km t sirve como parte d pago | F318: Dale pero si es plan t digo q no m interesa | G318: Whatsapp | H318: Amba | I318: Autos del Sol | J318: 45834
A319: 2025-06-26T17:53:55-03:00 | B319: Nicolás Garnica | C319: 5491152215437 | D319: Moreno | E319: Cronos | F319: En este momento no hay problema | G319: Whatsapp | H319: Amba | I319: Autos del Sol | J319: 45834
A320: 2025-06-26T17:57:50-03:00 | B320: Nano | C320: 5491135764960 | D320: Merlo | E320: Si | F320: De 18 a 21hs | G320: Whatsapp | H320: Amba | I320: Autos del Sol | J320: 45834
A321: 2025-06-26T17:12:15-03:00 | B321: Nestor | C321: 5492993291494 | D321: amba | E321: Cronos | F321: llamar por la tarde | G321: Whatsapp | H321: Amba | I321: Autos del Sol | J321: 45834
A322: 2025-06-26T17:51:16-03:00 | B322: leonardohermosa4 | C322: 5491168708215 | D322: En Buenos Aires Francisco Álvarez | E322: Q es Cronos , u otro | F322: Ahora | G322: Whatsapp | H322: Amba | I322: Autos del Sol | J322: 45834
A323: 2025-06-26T18:19:44-03:00 | B323: 💪🏻😎🇻🇪Oliver🇻🇪😎👍🏻 | C323: 5491138658992 | D323: Ceonos | E323: Hola cómo seria el tema de mini cuota | F323: Zona oeste | G323: Whatsapp | H323: Amba | I323: Autos del Sol | J323: 45834
A324: 2025-06-26T17:34:58-03:00 | B324: Mostró 25 | C324: 5491123209562 | D324: amba | E324: Cronos | F324: llamar por la tarde | G324: Whatsapp | H324: Amba | I324: Autos del Sol | J324: 45834
A325: 2025-06-26T18:38:55-03:00 | B325: Nano | C325: 5491130746563 | D325: Soy de marcos paz | E325: Hola buenas tardes me gustaria conprar un strada | F325: Recien llego a casa | G325: Whatsapp | H325: Amba | I325: Autos del Sol | J325: 45834
A326: 2025-06-26T17:50:53-03:00 | B326: Beto Beto | C326: 5491136170600 | D326: Vte lopez | E326: Fiat strada | F326: llamar por la tarde | G326: Whatsapp | H326: Amba | I326: Autos del Sol | J326: 45834
... A329: 2025-06-26T18:16:08-03:00 | B329: Soy Feliz | C329: 5493489659657 | D329: amba | E329: Otro | F329: llamar por la tarde | G329: Whatsapp | H329: Amba | I329: Autos del Sol | J329: 45834
A330: 2025-06-26T19:50:11-03:00 | B330: Oscar | C330: 5491160304305 | D330: Merlo | E330: Estrada 4puertas | F330: 0.45833333 | G330: Whatsapp | H330: Amba | I330: Autos del Sol | J330: 45834
A331: 2025-06-26T19:15:44-03:00 | B331: Facu | C331: 5491122538809 | D331: amba | E331: Cronos | F331: llamar por la tarde | G331: Whatsapp | H331: Amba | I331: Autos del Sol | J331: 45834
A332: 2025-06-26T20:04:45-03:00 | B332: Jorge Omar Campos | C332: 5491126384878 | D332: Ok | E332: Cronos | F332: Mañana tipo 12 hs | G332: Whatsapp | H332: Amba | I332: Autos del Sol | J332: 45834
A333: 2025-06-26T20:31:04-03:00 | B333: Stella | C333: 5492323680596 | D333: Ok | E333: Crono | F333: Mañana a la mañana | G333: Whatsapp | H333: Amba | I333: Autos del Sol | J333: 45834
A334: 2025-06-26T19:35:19-03:00 | B334: 🔴⚪⚫ | C334: 5491128052982 | D334: amba | E334: Cronos | F334: llamar por la tarde | G334: Whatsapp | H334: Amba | I334: Autos del Sol | J334: 45834
A335: 2025-06-26T20:30:52-03:00 | B335: marquezyaninasoledad06 | C335: 5491123861711 | D335: San Martin Buenos días | E335: Hola Crono | F335: 8hs AM a 15 pm | G335: Whatsapp | H335: Amba | I335: Autos del Sol | J335: 45834
A336: 2025-06-26T20:40:18-03:00 | B336: Pol | C336: 5491135742661 | D336: amba | E336: Cronos | F336: llamar por la tarde | G336: Whatsapp | H336: Amba | I336: Autos del Sol | J336: 45834
A337: 2025-06-26T20:45:01-03:00 | B337: 😍 | C337: 5491144043006 | D337: amba | E337: Cronos | F337: llamar por la tarde | G337: Whatsapp | H337: Amba | I337: Autos del Sol | J337: 45834
A338: 2025-06-26T21:53:14-03:00 | B338: !!!!!!!!!!!!!!!!! | C338: 5492617050976 | D338: Mendoza | E338: Cronos | F338: Quiero más información del 0km | G338: Whatsapp | H338: Amba | I338: Autos del Sol | J338: 45834
A339: 2025-06-26T21:16:25-03:00 | B339: damian | C339: 5493487307420 | D339: amba | E339: Cronos | F339: llamar por la tarde | G339: Whatsapp | H339: Amba | I339: Autos del Sol | J339: 45834
A340: 2025-06-26T21:35:28-03:00 | B340: Elías German Luna | C340: 5493731538566 | D340: amba | E340: Cronos | F340: llamar por la tarde | G340: Whatsapp | H340: Amba | I340: Autos del Sol | J340: 45834
A341: 2025-06-26T21:49:34-03:00 | B341: Javo | C341: 5491165992821 | D341: amba | E341: Cronos | F341: llamar por la tarde | G341: Whatsapp | H341: Amba | I341: Autos del Sol | J341: 45834
A342: 2025-06-26T22:05:20-03:00 | B342: Mario Cordoba | C342: 5491166243788 | D342: Hurlingham | E342: Cronos | F342: llamar por la tarde | G342: Whatsapp | H342: Amba | I342: Autos del Sol | J342: 45834
... A349: 2025-06-27T00:58:02-03:00 | B349: Maluma Beybe On De World | C349: 5491138513664 | D349: amba | E349: Cronos | F349: llamar por la tarde | G349: Whatsapp | H349: Amba | I349: Autos del Sol | J349: 45835
A350: 2025-06-27T02:34:55-03:00 | B350: Lucas | C350: 5491154954738 | D350: Florencio varela | E350: El mas economico | F350: 14 | G350: Whatsapp | H350: Amba | I350: Autos del Sol | J350: 45835
A351: 2025-06-27T03:18:19-03:00 | B351: Fernando Borruso | C351: 5491124997220 | D351: Wilde | E351: Solo con el DNI se retiro y voy pagando?? Es para trabajar | F351: 14 hs | G351: Whatsapp | H351: Amba | I351: Autos del Sol | J351: 45835
A352: 2025-06-27T02:53:03-03:00 | B352: El Groso | C352: 5491126206744 | D352: amba | E352: Cronos | F352: llamar por la tarde | G352: Whatsapp | H352: Amba | I352: Autos del Sol | J352: 45835
A353: 2025-06-27T05:42:05-03:00 | B353: Raaa 😅 | C353: 5491134202044 | D353: amba | E353: Otro | F353: llamar por la tarde | G353: Whatsapp | H353: Amba | I353: Autos del Sol | J353: 45835
A354: 2025-06-27T07:08:00-03:00 | B354: Empresa Constructora SA | C354: 5491164097481 | D354: Máximo paz | E354: Crono | F354: A l 12 10 | G354: Whatsapp | H354: Amba | I354: Autos del Sol | J354: 45835
A355: 2025-06-27T07:11:16-03:00 | B355: Henry | C355: 5491131633668 | D355: Pilar | E355: Cronos | F355: Mañana | G355: Whatsapp | H355: Amba | I355: Autos del Sol | J355: 45835
A356: 2025-06-27T07:17:37-03:00 | B356: vía sano y flex salud | C356: 5491153152720 | D356: Oeste | E356: Otro | F356: llamar por la tarde | G356: Whatsapp | H356: Amba | I356: Autos del Sol | J356: 45835
A357: 2025-06-27T08:25:56-03:00 | B357: Juan Cruz Fernandez | C357: 5491126520208 | D357: V.lopez | E357: Argo okm | F357: Me gustaría sacarlo al 100x100 financiado en color rojo | G357: Whatsapp | H357: Amba | I357: Autos del Sol | J357: 45835
A358: 2025-06-27T08:14:05-03:00 | B358: Roberto Pereyra | C358: 5491151812147 | D358: amba | E358: Cronos | F358: llamar por la tarde | G358: Whatsapp | H358: Amba | I358: Autos del Sol | J358: 45835
A359: 2025-06-27T08:52:47-03:00 | B359: Rolandoestebanolivo | C359: 5491138224769 | D359: amba | E359: Cronnos | F359: llamar por la tarde | G359: Whatsapp | H359: Amba | I359: Autos del Sol | J359: 45835
A360: 2025-06-27T09:10:16-03:00 | B360: Ámbar💜 | C360: 5491122594804 | D360: amba | E360: Cronos | F360: llamar por la tarde | G360: Whatsapp | H360: Amba | I360: Autos del Sol | J360: 45835
A361: 2025-06-27T10:35:14-03:00 | B361: Walter | C361: 5491169257177 | D361: Transradio barrio 9 de Abril Esteban Echeberria | E361: Estrada | F361: 20 horas | G361: Whatsapp | H361: Amba | I361: Autos del Sol | J361: 45835
A362: 2025-06-27T10:51:22-03:00 | B362: Victor | C362: 5493705398204 | D362: Ok | E362: Cronos | F362: De la 17 horas | G362: Whatsapp | H362: Amba | I362: Autos del Sol | J362: 45835
... A442: 2025-06-30T13:36:29-03:00 | B442: Lucho | C442: 5491166296773 | D442: Zona Nortes Tigre Bs.As. | E442: Fiat Astrada👍 | F442: llamar por la tarde | G442: Whatsapp | H442: Amba | I442: Autos del Sol | J442: 45838
A443: 2025-06-30T15:26:09-03:00 | B443: Ruben Chavez | C443: 5491162820999 | D443: Lomas | E443: Hola soy ruben | F443: 4 | G443: Whatsapp | H443: Amba | I443: Autos del Sol | J443: 45838
A444: 2025-06-30T14:46:48-03:00 | B444: Ale Clau | C444: 5491158224093 | D444: amba | E444: Cronos | F444: llamar por la tarde | G444: Whatsapp | H444: Amba | I444: Autos del Sol | J444: 45838
...

Sheet Toyota
A1: Fecha | B1: Nombre | C1: Telefono | D1: Localidad | E1: Modelo | F1: Horario / Comentarios | G1: ORIGEN | H1: LOCALIZACION | I1: CLIENTE | J1: Formula 1 | K1: Formula 2 | L1: Conteo de leads | M1: Fecha | N1: TOTAL LEADS
A2: 2025-07-06T04:00:39-03:00 | B2: markoss👽👽 | C2: 5491161268319 | D2: amba | E2: Yaris | F2: llamar por la tarde | G2: Whatsapp | H2: Amba | I2: Mariano - Pichetti | J2: {=IF(A2:A1821="", "", DATE(LEFT(A2:A1821,4)*1, MID(A2:A1821,6,2)*1, MID(A2:A1821,9,2)*1))} -> 45844 | K2: {=UNIQUE(J2:J1821)} -> 45844 | L2: {=IF(K2:K1821="", "", COUNTIF(J2:J1821, K2:K1821))} -> 7 | M2: {=IF(K2:K1821="", "", TEXT(K2:K1821, "dd/mm/yyyy"))} -> 06/07/2025 | N2: =SUM(L2:L1821) -> 82
A3: 2025-07-06T06:47:07-03:00 | B3: la mejor | C3: 5491158583622 | D3: amba | E3: Corolla | F3: llamar por la tarde | G3: Whatsapp | H3: Amba | I3: Mariano - Pichetti | J3: 45844 | K3: 45845 | L3: 9 | M3: 07/07/2025
A4: 2025-07-06T14:46:02-03:00 | B4: Jorgecarrasco | C4: 5491124928292 | D4: Lomas de Zamora | E4: Yaris o otro 4 puertas | F4: Después de 20 hs | G4: Whatsapp | H4: Amba | I4: Mariano - Pichetti | J4: 45844 | K4: 45846 | L4: 7 | M4: 08/07/2025
A5: 2025-07-06T16:48:28-03:00 | B5: . | C5: 5492213551096 | D5: amba | E5: Corolla | F5: llamar por la tarde | G5: Whatsapp | H5: Amba | I5: Mariano - Pichetti | J5: 45844 | K5: 45847 | L5: 13 | M5: 09/07/2025
A6: 2025-07-06T16:56:36-03:00 | B6: Mario Luque | C6: 5491121907531 | D6: amba | E6: Corolla | F6: llamar por la tarde | G6: Whatsapp | H6: Amba | I6: Mariano - Pichetti | J6: 45844 | K6: 45848 | L6: 6 | M6: 10/07/2025
A7: 2025-07-06T18:10:08-03:00 | B7: Rubén Drago | C7: 5491134706603 | D7: Martinez | E7: Yaris | F7: llamar por la tarde | G7: Whatsapp | H7: Amba | I7: Mariano - Pichetti | J7: 45844 | K7: 45849 | L7: 7 | M7: 11/07/2025
A8: 2025-07-06T23:28:16-03:00 | B8: luis campopiano | C8: 5491127001718 | D8: amba | E8: Corolla | F8: llamar por la tarde | G8: Whatsapp | H8: Amba | I8: Mariano - Pichetti | J8: 45844 | K8: 45850 | L8: 8 | M8: 12/07/2025
A9: 2025-07-07T10:40:33-03:00 | B9: Mar Benve | C9: 5491165286440 | D9: Caba | E9: Yaris | F9: Todo el día | G9: Whatsapp | H9: Amba | I9: Mariano - Pichetti | J9: 45845 | K9: 45851 | L9: 10 | M9: 13/07/2025
A10: 2025-07-07T12:58:09-03:00 | B10: Mi Pepi | C10: 5491168204221 | D10: Retro | E10: Yatis | F10: Tarde | G10: Whatsapp | H10: Amba | I10: Mariano - Pichetti | J10: 45845 | K10: 45852 | L10: 11 | M10: 14/07/2025
A11: 2025-07-07T16:25:03-03:00 | B11: Jesus Ramon Andino | C11: 5493516105567 | D11: Caba. Belgrano | E11: Yaris | F11: Podes ahora ?? | G11: Whatsapp | H11: Amba | I11: Mariano - Pichetti | J11: 45845 | K11: 45853 | L11: 4 | M11: 15/07/2025
A12: 2025-07-07T16:36:32-03:00 | B12: Daniel Rodríguez | C12: 5492267418622 | D12: Madariaga | E12: Hilux | F12: llamar por la tarde | G12: Whatsapp | H12: Amba | I12: Mariano - Pichetti | J12: 45845
A13: 2025-07-07T16:43:58-03:00 | B13: Imgresos Salud mental | C13: 5491139346157 | D13: amba | E13: Corolla | F13: llamar por la tarde | G13: Whatsapp | H13: Amba | I13: Mariano - Pichetti | J13: 45845
A14: 2025-07-07T16:50:01-03:00 | B14: Mi Alma Mi Vida Toda | C14: 5492233120340 | D14: amba | E14: Corolla | F14: llamar por la tarde | G14: Whatsapp | H14: Amba | I14: Mariano - Pichetti | J14: 45845
A15: 2025-07-07T20:03:22-03:00 | B15: Diego | C15: 5491126058598 | D15: Vicecente lopez | E15: Hilux | F15: Ahora | G15: Whatsapp | H15: Amba | I15: Mariano - Pichetti | J15: 45845
A16: 2025-07-07T22:45:28-03:00 | B16: Sebas | C16: 5491161172314 | D16: Pilar | E16: Corolla | F16: 9:00 am | G16: Whatsapp | H16: Amba | I16: Mariano - Pichetti | J16: 45845
A17: 2025-07-07T23:33:47-03:00 | B17: Adrian | C17: 5491123775197 | D17: Zona sur avellaneda | E17: Corolla | F17: Tomando usado de 10 a 14 | G17: Whatsapp | H17: Amba | I17: Mariano - Pichetti | J17: 45845
A18: 2025-07-08T00:35:41-03:00 | B18: Jose Luis Contreras Salu | C18: 5491164273381 | D18: Quilmes | E18: Hilux | F18: Cuando puedas | G18: Whatsapp | H18: Amba | I18: Mariano - Pichetti | J18: 45846
A19: 2025-07-08T00:17:31-03:00 | B19: Leandro Tissoni | C19: 5492355463850 | D19: amba | E19: Corolla | F19: llamar por la tarde | G19: Whatsapp | H19: Amba | I19: Mariano - Pichetti | J19: 45846
A20: 2025-07-08T06:34:30-03:00 | B20: julian flores | C20: 5491155796021 | D20: amba | E20: Corolla | F20: llamar por la tarde | G20: Whatsapp | H20: Amba | I20: Mariano - Pichetti | J20: 45846
A21: 2025-07-08T08:16:32-03:00 | B21: Gaston | C21: 5491127563706 | D21: amba | E21: Corolla | F21: llamar por la tarde | G21: Whatsapp | H21: Amba | I21: Mariano - Pichetti | J21: 45846
A22: 2025-07-08T14:12:17-03:00 | B22: Rolo | C22: 5492233486450 | D22: Mardel plata | E22: Corolla | F22: llamar por la tarde | G22: Whatsapp | H22: Amba | I22: Mariano - Pichetti | J22: 45846
A23: 2025-07-08T15:02:19-03:00 | B23: Fabi | C23: 5493777404671 | D23: amba | E23: Corolla | F23: llamar por la tarde | G23: Whatsapp | H23: Amba | I23: Mariano - Pichetti | J23: 45846
... A25: 2025-07-09T09:35:41-03:00 | B25: Domingo | C25: 5491157255097 | D25: Ok | E25: Corolla | F25: Se puede contactar a partir de las 9 hrs en adelante | G25: Whatsapp | H25: Amba | I25: Mariano - Pichetti | J25: 45847
A26: 2025-07-09T10:17:39-03:00 | B26: Claudio | C26: 5491162912280 | D26: Merlo | E26: Corolla | F26: 1162912280 | G26: Whatsapp | H26: Amba | I26: Mariano - Pichetti | J26: 45847
A27: 2025-07-09T09:44:45-03:00 | B27: Jose | C27: 5491127999846 | D27: amba | E27: Corolla | F27: llamar por la tarde | G27: Whatsapp | H27: Amba | I27: Mariano - Pichetti | J27: 45847
A28: 2025-07-09T11:11:33-03:00 | B28: Patricia Ferrero | C28: 5492342558561 | D28: BRAGADO provincia de Buenos Aires | E28: Corolla | F28: Después de las 16 y 30 hs | G28: Whatsapp | H28: Amba | I28: Mariano - Pichetti | J28: 45847
A29: 2025-07-09T10:50:10-03:00 | B29: ❄️🌸🍋🍊🥭🍪🍬🐬🫵🏾 | C29: 5491136813214 | D29: amba | E29: Corolla | F29: llamar por la tarde | G29: Whatsapp | H29: Amba | I29: Mariano - Pichetti | J29: 45847
A30: 2025-07-09T14:26:03-03:00 | B30: demetriotorales | C30: 5491167031533 | D30: Soy de mariano Acosta partido de Merlo | E30: Hola quétal una Toyota Hilux | F30: Durante por la mañana sin problema | G30: Whatsapp | H30: Amba | I30: Mariano - Pichetti | J30: 45847
A31: 2025-07-09T17:08:43-03:00 | B31: Richi | C31: 5491136413551 | D31: Avellaneda | E31: Corolla | F31: En la tarde | G31: Whatsapp | H31: Amba | I31: Mariano - Pichetti | J31: 45847
A32: 2025-07-09T17:10:17-03:00 | B32: Mario | C32: 5491150103017 | D32: Ramos Mejía | E32: Corolla | F32: Cualquier horario | G32: Whatsapp | H32: Amba | I32: Mariano - Pichetti | J32: 45847
A33: 2025-07-09T18:32:52-03:00 | B33: Gaston | C33: 5491162490000 | D33: Quilmes | E33: Corola | F33: 0.70833333 | G33: Whatsapp | H33: Amba | I33: Mariano - Pichetti | J33: 45847
A34: 2025-07-09T18:22:01-03:00 | B34: Pedro | C34: 5491160012019 | D34: Grandbourg | E34: Hilux | F34: llamar por la tarde | G34: Whatsapp | H34: Amba | I34: Mariano - Pichetti | J34: 45847
A35: 2025-07-09T19:33:04-03:00 | B35: Luciano Valenzuela | C35: 5491151499379 | D35: Pilar | E35: Yaris | F35: Mañana | G35: Whatsapp | H35: Amba | I35: Mariano - Pichetti | J35: 45847
A36: 2025-07-09T22:07:50-03:00 | B36: Naino | C36: 5491157826395 | D36: Sona sur | E36: Corola | F36: llamar por la tarde | G36: Whatsapp | H36: Amba | I36: Mariano - Pichetti | J36: 45847
A37: 2025-07-09T22:32:55-03:00 | B37: Dioni | C37: 5493884719694 | D37: amba | E37: Corolla | F37: llamar por la tarde | G37: Whatsapp | H37: Amba | I37: Mariano - Pichetti | J37: 45847
A38: 2025-07-10T06:36:33-03:00 | B38: Franco | C38: 5491178431076 | D38: Puedo entregar un dinero y el resto en cuotas | E38: Cómo compro una Toyota Hilux | F38: Don Torcuato | G38: Whatsapp | H38: Amba | I38: Mariano - Pichetti | J38: 45848
A39: 2025-07-10T08:50:01-03:00 | B39: Rafael Monzón | C39: 5491134255877 | D39: Vivo en San Miguel buenos aires | E39: Me interesa un Toyota Corolla que precio está, | F39: Si puede ahora o a partir de las 14 horas | G39: Whatsapp | H39: Amba | I39: Mariano - Pichetti | J39: 45848
A40: 2025-07-10T09:57:59-03:00 | B40: Sergio Daniel Solís | C40: 5491162145822 | D40: amba | E40: Hilux | F40: llamar por la tarde | G40: Whatsapp | H40: Amba | I40: Mariano - Pichetti | J40: 45848
A41: 2025-07-10T12:22:02-03:00 | B41: Diego | C41: 5491156472776 | D41: Nuevo | E41: Corola | F41: Quilmes sona sur | G41: Whatsapp | H41: Amba | I41: Mariano - Pichetti | J41: 45848
A42: 2025-07-10T16:30:30-03:00 | B42: veymar Blanco | C42: 5491168042349 | D42: Cochabamba | E42: Corolla | F42: llamar por la tarde | G42: Whatsapp | H42: Amba | I42: Mariano - Pichetti | J42: 45848
A43: 2025-07-10T16:58:33-03:00 | B43: Mariam | C43: 5491168011498 | D43: Lanus | E43: Corola | F43: llamar por la tarde | G43: Whatsapp | H43: Amba | I43: Mariano - Pichetti | J43: 45848
A44: 2025-07-11T06:27:30-03:00 | B44: Fer | C44: 5491135425109 | D44: Zona oeste | E44: Corolla | F44: Después de las 15hs | G44: Whatsapp | H44: Amba | I44: Mariano - Pichetti | J44: 45849
A45: 2025-07-11T10:52:11-03:00 | B45: Fausto Ojeda | C45: 5491154119962 | D45: General Pacheco | E45: Otro | F45: Quiero saber de un auto económico, financiado al 100% , y me pueden contactar desde de las 18 | G45: Whatsapp | H45: Amba | I45: Mariano - Pichetti | J45: 45849
... A83: 2025-07-15T22:27:45-03:00 | B83: Carlos😁 | C83: 5491168085492 | D83: amba | E83: Corolla | F83: llamar por la tarde | G83: Whatsapp | H83: Amba | I83: Mariano - Pichetti | J83: 45853

Sheet Chevrolet
A1: Fecha | B1: Nombre | C1: Telefono | D1: Localidad | E1: Modelo | F1: Horario / Comentarios | G1: ORIGEN | H1: LOCALIZACION | I1: CLIENTE | J1: Formula 1 | K1: Formula 2 | L1: Conteo de leads | M1: Fecha | N1: TOTAL LEADS
A2: 2025-07-14T12:02:41-03:00 | B2: 💙🩷💙💙🩷💙 L.L.P.J.B.S | C2: 5492392688243 | D2: Trenque lauquen | E2: El más económico de chevrolet | F2: De 14 a 20hs | G2: Whatsapp | H2: Amba | I2: Chevrolet Italy | J2: {=IF(A2:A1048="", "", DATE(LEFT(A2:A1048,4)*1, MID(A2:A1048,6,2)*1, MID(A2:A1048,9,2)*1))} -> 45852 | K2: {=UNIQUE(J2:J1048)} -> 45852 | L2: {=IF(K2:K1048="", "", COUNTIF(J2:J1048, K2:K1048))} -> 17 | M2: {=IF(K2:K1048="", "", TEXT(K2:K1048, "dd/mm/yyyy"))} -> 14/07/2025 | N2: =SUM(L2:L1856) -> 47
A3: 2025-07-14T12:48:16-03:00 | B3: Luis Romero | C3: 5493625196255 | D3: amba | E3: Hola la montana | F3: llamar por la tarde | G3: Whatsapp | H3: Amba | I3: Chevrolet Italy | J3: 45852 | K3: 45853 | L3: 28 | M3: 15/07/2025
A4: 2025-07-14T14:40:28-03:00 | B4: Aldo | C4: 5492664661058 | D4: San luis capital | E4: Onix | F4: llamar por la tarde | G4: Whatsapp | H4: Amba | I4: Chevrolet Italy | J4: 45852 | K4: 45854 | L4: 2 | M4: 16/07/2025
A5: 2025-07-14T17:21:08-03:00 | B5: Luciano | C5: 5493515153829 | D5: Cordoba | E5: Onix tracker | F5: Alas 9 de la mañana | G5: Whatsapp | H5: Amba | I5: Chevrolet Italy | J5: 45852
A6: 2025-07-14T17:42:04-03:00 | B6: Jcvd | C6: 5492954653421 | D6: Toay la pampa | E6: Me pasas presio de la Traker cero km | F6: Ahora | G6: Whatsapp | H6: Amba | I6: Chevrolet Italy | J6: 45852
A7: 2025-07-14T17:25:15-03:00 | B7: 🤩cc | C7: 5493754430917 | D7: amba | E7: Onix | F7: llamar por la tarde | G7: Whatsapp | H7: Amba | I7: Chevrolet Italy | J7: 45852
A8: 2025-07-14T17:30:49-03:00 | B8: Moises | C8: 5493757310447 | D8: amba | E8: Onix | F8: llamar por la tarde | G8: Whatsapp | H8: Amba | I8: Chevrolet Italy | J8: 45852
A9: 2025-07-14T18:37:11-03:00 | B9: Ceferino manuel Aragon | C9: 5491150410323 | D9: Soy de san Martín | E9: Tracker | F9: Reciben plan caídos tengo 2 | G9: Whatsapp | H9: Amba | I9: Chevrolet Italy | J9: 45852
A10: 2025-07-14T18:43:24-03:00 | B10: Gregorio Guanco | C10: 5491126867399 | D10: Nos o uno con motor 1.4 y baúl | E10: Sera verdad | F10: llamar por la tarde | G10: Whatsapp | H10: Amba | I10: Chevrolet Italy | J10: 45852
A11: 2025-07-14T18:57:07-03:00 | B11: Mirta Saavedra | C11: 5493704375993 | D11: amba | E11: S10 | F11: llamar por la tarde | G11: Whatsapp | H11: Amba | I11: Chevrolet Italy | J11: 45852
A12: 2025-07-14T20:32:15-03:00 | B12: iriarteruben621 | C12: 5491124032942 | D12: Berazategui | E12: Onix caja automática | F12: Bien. Desde 14 hs en adelante | G12: Whatsapp | H12: Amba | I12: Chevrolet Italy | J12: 45852
A13: 2025-07-14T20:41:58-03:00 | B13: MARTIN RIOS | C13: 5492625525681 | D13: amba | E13: Onix | F13: llamar por la tarde | G13: Whatsapp | H13: Amba | I13: Chevrolet Italy | J13: 45852
A14: 2025-07-14T21:46:14-03:00 | B14: Taller Luis The Hammer | C14: 5493751306611 | D14: En misiones eldorado | E14: ONIX | F14: De 8 a 19 horas | G14: Whatsapp | H14: Amba | I14: Chevrolet Italy | J14: 45852
A15: 2025-07-14T21:18:08-03:00 | B15: Juan abel Argañaraz | C15: 5491139220272 | D15: amba | E15: Hole gente | F15: llamar por la tarde | G15: Whatsapp | H15: Amba | I15: Chevrolet Italy | J15: 45852
A16: 2025-07-14T21:19:46-03:00 | B16: Gabriel Cáceres | C16: 5491162134701 | D16: amba | E16: Onix | F16: llamar por la tarde | G16: Whatsapp | H16: Amba | I16: Chevrolet Italy | J16: 45852
... A48: 2025-07-16T10:15:29-03:00 | B48: Dios es fiel | C48: 5493624772542 | D48: Resistencia chaco | E48: Onix | F48: Si ahora estoy disponible | G48: Whatsapp | H48: Amba | I48: Chevrolet Italy | J48: 45854

Sheet Renault
A1: Fecha | B1: Nombre | C1: Telefono | D1: Localidad | E1: Modelo | F1: Horario / Comentarios | G1: ORIGEN | H1: LOCALIZACION | I1: CLIENTE | J1: Formula 1 | K1: Formula 2 | L1: Conteo de leads | M1: Fecha | N1: TOTAL LEADS
A2: 2025-07-14T16:12:53-03:00 | B2: Hector | C2: 5491140943116 | D2: Caba Soldati | E2: Kangoo combinada gracias | F2: Me gustaría en el local | G2: Whatsapp | H2: Amba | I2: Javier Cagiao | J2: {=IF(A2:A1023="", "", DATE(LEFT(A2:A1023,4)*1, MID(A2:A1023,6,2)*1, MID(A2:A1023,9,2)*1))} -> 45852 | K2: {=UNIQUE(J2:J1023)} -> 45852 | L2: {=IF(K2:K1023="", "", COUNTIF(J2:J1023, K2:K1023))} -> 7 | M2: {=IF(K2:K1023="", "", TEXT(K2:K1023, "dd/mm/yyyy"))} -> 14/07/2025 | N2: =SUM(L2:L1839) -> 20
A3: 2025-07-14T18:04:40-03:00 | B3: 5491158720915 | C3: 5491158720915 | D3: Capital, Monserrat | E3: Kangoo | F3: llamar por la tarde | G3: Whatsapp | H3: Amba | I3: Javier Cagiao | J3: 45852 | K3: 45853 | L3: 12 | M3: 15/07/2025
A4: 2025-07-14T19:21:52-03:00 | B4: Emiliano | C4: 5492645731464 | D4: Rawson san juan | E4: Kangoo | F4: Desd las 18hs en adelante | G4: Whatsapp | H4: Amba | I4: Javier Cagiao | J4: 45852 | K4: 45854 | L4: 1 | M4: 16/07/2025
A5: 2025-07-14T19:15:15-03:00 | B5: Kary | C5: 5491122979759 | D5: Tablada | E5: Kanguo | F5: 14hs | G5: Whatsapp | H5: Amba | I5: Javier Cagiao | J5: 45852
A6: 2025-07-14T20:29:05-03:00 | B6: Lucas | C6: 5491131438895 | D6: amba | E6: Kwid | F6: llamar por la tarde | G6: Whatsapp | H6: Amba | I6: Javier Cagiao | J6: 45852
A7: 2025-07-14T22:49:14-03:00 | B7: Juli.sala | C7: 5491162867075 | D7: Color Roja | E7: La kardian | F7: Tipo 14 hs | G7: Whatsapp | H7: Amba | I7: Javier Cagiao | J7: 45852
A8: 2025-07-14T22:20:30-03:00 | B8: Oscar | C8: 5491121736343 | D8: amba | E8: Kwid | F8: llamar por la tarde | G8: Whatsapp | H8: Amba | I8: Javier Cagiao | J8: 45852
A9: 2025-07-15T05:33:02-03:00 | B9: Jose | C9: 5491122666749 | D9: amba | E9: Kwid | F9: llamar por la tarde | G9: Whatsapp | H9: Amba | I9: Javier Cagiao | J9: 45853
A10: 2025-07-15T07:42:51-03:00 | B10: Miguel | C10: 5491162763071 | D10: Ciudadela | E10: Kangoo | F10: Después delas 6 pm | G10: Whatsapp | H10: Amba | I10: Javier Cagiao | J10: 45853
A11: 2025-07-15T07:57:27-03:00 | B11: Skyhawk | C11: 5491152606837 | D11: Okey | E11: Él auto kwid | F11: En el dia ahora | G11: Whatsapp | H11: Amba | I11: Javier Cagiao | J11: 45853
A12: 2025-07-15T08:20:13-03:00 | B12: Henrry Cardozo | C12: 5493875513462 | D12: Buenos aires capital | E12: Kangoo | F12: En la mañana | G12: Whatsapp | H12: Amba | I12: Javier Cagiao | J12: 45853
A13: 2025-07-15T08:41:17-03:00 | B13: ❤️🥰 | C13: 5491158335393 | D13: Ok | E13: Kangoo | F13: Kangoo 5 asientos | G13: Whatsapp | H13: Amba | I13: Javier Cagiao | J13: 45853
A14: 2025-07-15T10:11:58-03:00 | B14: Damian Carrasco | C14: 5491168385245 | D14: San Martín | E14: Kangoo | F14: 0.75 | G14: Whatsapp | H14: Amba | I14: Javier Cagiao | J14: 45853
A15: 2025-07-15T13:04:23-03:00 | B15: Ricky | C15: 5491161700009 | D15: amba | E15: Kangoo | F15: llamar por la tarde | G15: Whatsapp | H15: Amba | I15: Javier Cagiao | J15: 45853
A16: 2025-07-15T15:07:01-03:00 | B16: Skyhawk | C16: 5491152606837 | D16: Virrey del pino | E16: Kwid | F16: Ahora | G16: Whatsapp | H16: Amba | I16: Javier Cagiao | J16: 45853
A17: 2025-07-15T18:58:33-03:00 | B17: Arturo | C17: 5491158642404 | D17: Exaltacion de la cruz | E17: Kangoo | F17: De 9 a 15 | G17: Whatsapp | H17: Amba | I17: Javier Cagiao | J17: 45853
A18: 2025-07-15T19:24:31-03:00 | B18: Raquel Tarantelli | C18: 5491136051477 | D18: Lanús oeste | E18: Kangoo | F18: llamar por la tarde | G18: Whatsapp | H18: Amba | I18: Javier Cagiao | J18: 45853
A19: 2025-07-15T23:17:07-03:00 | B19: ADMINISTRACION | C19: 59175244900 | D19: amba | E19: Kwid | F19: llamar por la tarde | G19: Whatsapp | H19: Amba | I19: Javier Cagiao | J19: 45853
A20: 2025-07-15T22:36:40-03:00 | B20: Brian | C20: 5491125331131 | D20: amba | E20: Kangoo | F20: llamar por la tarde | G20: Whatsapp | H20: Amba | I20: Javier Cagiao | J20: 45853
A21: 2025-07-16T01:08:31-03:00 | B21: GO CLICK! | C21: 5491126328889 | D21: Don Torcuato | E21: Kangoo | F21: A partir de las 10 | G21: Whatsapp | H21: Amba | I21: Javier Cagiao | J21: 45854

Sheet Citroen
A1: Fecha | B1: Nombre | C1: Telefono | D1: Localidad | E1: Modelo | F1: Horario / Comentarios | G1: ORIGEN | H1: LOCALIZACION | I1: CLIENTE | J1: Formula 1 | K1: Formula 2 | L1: Conteo de leads | M1: Fecha | N1: TOTAL LEADS
